fixy/__init__.py
fixy-0.0.0.dist-info/METADATA
fixy-0.0.0.dist-info/WHEEL
fixy-0.0.0.dist-info/top_level.txt
fixy-0.0.0.dist-info/RECORD
