Metadata-Version: 2.4
Name: fixy
Version: 0.0.0
Summary: Coming soon
Author-email: John Hudson <jh@ingratexr.com>
